hiveplotlib/__init__.py
hiveplotlib/axis.py
hiveplotlib/converters.py
hiveplotlib/edges.py
hiveplotlib/hiveplot.py
hiveplotlib/node.py
hiveplotlib/p2cp.py
hiveplotlib/utils.py
hiveplotlib/datasets/__init__.py
hiveplotlib/datasets/international_trade.py
hiveplotlib/datasets/toy_hive_plots.py
hiveplotlib/datasets/toy_p2cps.py
hiveplotlib/datasets/trade_data_harvard_growth_lab/international_exports_2019_8112.csv
hiveplotlib/datasets/trade_data_harvard_growth_lab/international_exports_metadata_2019_8112.json
hiveplotlib/exceptions/__init__.py
hiveplotlib/exceptions/hive_plot.py
hiveplotlib/exceptions/node.py
hiveplotlib/viz/__init__.py
hiveplotlib/viz/base.py
hiveplotlib/viz/bokeh.py
hiveplotlib/viz/datashader.py
hiveplotlib/viz/holoviews.py
hiveplotlib/viz/input_checks.py
hiveplotlib/viz/matplotlib.py
hiveplotlib/viz/plotly.py
hiveplotlib-0.26.2.dist-info/licenses/LICENSE
hiveplotlib-0.26.2.dist-info/METADATA
hiveplotlib-0.26.2.dist-info/WHEEL
hiveplotlib-0.26.2.dist-info/top_level.txt
hiveplotlib-0.26.2.dist-info/RECORD
