Metadata-Version: 2.4
Name: hiveplotlib
Version: 0.26.2
Summary: Visualize Network Data with Hive Plots
Author-email: Gary Koplik <gary.koplik@geomdata.com>
License: Copyright (c) 2020 - 2024, Geometric Data Analytics, Inc.
Project-URL: Documentation, https://hiveplotlib.readthedocs.io/stable/
Project-URL: Source, https://gitlab.com/geomdata/hiveplotlib
Requires-Python: >=3.10
License-File: LICENSE
Requires-Dist: matplotlib
Requires-Dist: numpy
Requires-Dist: pandas
Provides-Extra: bokeh
Requires-Dist: bokeh; extra == "bokeh"
Provides-Extra: datashader
Requires-Dist: dask[dataframe]; extra == "datashader"
Requires-Dist: datashader; extra == "datashader"
Requires-Dist: numba>0.54.0; extra == "datashader"
Requires-Dist: seaborn; extra == "datashader"
Provides-Extra: dev
Requires-Dist: bokeh; extra == "dev"
Requires-Dist: cartopy; extra == "dev"
Requires-Dist: dask[dataframe]; extra == "dev"
Requires-Dist: datashader; extra == "dev"
Requires-Dist: flexitext; extra == "dev"
Requires-Dist: geopandas; extra == "dev"
Requires-Dist: holoviews; extra == "dev"
Requires-Dist: jupyter; extra == "dev"
Requires-Dist: networkx; extra == "dev"
Requires-Dist: numba>0.54.0; extra == "dev"
Requires-Dist: plotly; extra == "dev"
Requires-Dist: pybadges; extra == "dev"
Requires-Dist: seaborn; extra == "dev"
Requires-Dist: tqdm; extra == "dev"
Provides-Extra: docs
Requires-Dist: myst-parser; extra == "docs"
Requires-Dist: nbsphinx; extra == "docs"
Requires-Dist: pydata-sphinx-theme; extra == "docs"
Requires-Dist: sphinx; extra == "docs"
Requires-Dist: sphinx-copybutton; extra == "docs"
Requires-Dist: toml; extra == "docs"
Provides-Extra: holoviews
Requires-Dist: bokeh; extra == "holoviews"
Requires-Dist: holoviews; extra == "holoviews"
Requires-Dist: numba>0.54.0; extra == "holoviews"
Provides-Extra: networkx
Requires-Dist: networkx; extra == "networkx"
Provides-Extra: plotly
Requires-Dist: plotly; extra == "plotly"
Provides-Extra: ruff
Requires-Dist: ruff; extra == "ruff"
Provides-Extra: testing
Requires-Dist: pytest; extra == "testing"
Requires-Dist: pytest-cov; extra == "testing"
Requires-Dist: pytest-html; extra == "testing"
Requires-Dist: pytest-timeout; extra == "testing"
Requires-Dist: pytest-xdist; extra == "testing"
Requires-Dist: toml; extra == "testing"
Dynamic: license-file
